{
    "title": "coho list-pulls report",
    "timestamp": "2016-11-03T18:39:37.894Z",
    "max-age": 1000,
    "repos": [
        {
            "repo": "cordova-android",
            "fresh-count": 8,
            "old-count": 0,
            "stale-count": 0,
            "total-count": 8,
            "message": "8 Pull Requests"
        },
        {
            "repo": "cordova-ios",
            "fresh-count": 6,
            "old-count": 0,
            "stale-count": 0,
            "total-count": 6,
            "message": "6 Pull Requests"
        },
        {
            "repo": "cordova-amazon-fireos",
            "fresh-count": 4,
            "old-count": 0,
            "stale-count": 0,
            "total-count": 4,
            "message": "4 Pull Requests"
        },
        {
            "repo": "cordova-windows",
            "fresh-count": 3,
            "old-count": 0,
            "stale-count": 0,
            "total-count": 3,
            "message": "3 Pull Requests"
        },
        {
            "repo": "cordova-ubuntu",
            "fresh-count": 3,
            "old-count": 0,
            "stale-count": 0,
            "total-count": 3,
            "message": "3 Pull Requests"
        },
        {
            "repo": "cordova-osx",
            "fresh-count": 1,
            "old-count": 0,
            "stale-count": 0,
            "total-count": 1,
            "message": "1 Pull Requests"
        },
        {
            "repo": "cordova-wp8",
            "fresh-count": 1,
            "old-count": 0,
            "stale-count": 0,
            "total-count": 1,
            "message": "1 Pull Requests"
        },
        {
            "repo": "cordova-browser",
            "fresh-count": 1,
            "old-count": 0,
            "stale-count": 0,
            "total-count": 1,
            "message": "1 Pull Requests"
        },
        {
            "repo": "cordova-tizen",
            "fresh-count": 1,
            "old-count": 0,
            "stale-count": 0,
            "total-count": 1,
            "message": "1 Pull Requests"
        },
        {
            "repo": "cordova-firefoxos",
            "fresh-count": 0,
            "old-count": 0,
            "stale-count": 0,
            "total-count": 0,
            "message": "0 Pull Requests"
        },
        {
            "repo": "cordova-blackberry",
            "fresh-count": 0,
            "old-count": 0,
            "stale-count": 0,
            "total-count": 0,
            "message": "0 Pull Requests"
        },
        {
            "repo": "cordova-bada",
            "fresh-count": 0,
            "old-count": 0,
            "stale-count": 0,
            "total-count": 0,
            "message": "0 Pull Requests"
        },
        {
            "repo": "cordova-bada-wac",
            "fresh-count": 0,
            "old-count": 0,
            "stale-count": 0,
            "total-count": 0,
            "message": "0 Pull Requests"
        },
        {
            "repo": "cordova-webos",
            "fresh-count": 0,
            "old-count": 0,
            "stale-count": 0,
            "total-count": 0,
            "message": "0 Pull Requests"
        },
        {
            "repo": "cordova-qt",
            "fresh-count": 0,
            "old-count": 0,
            "stale-count": 0,
            "total-count": 0,
            "message": "0 Pull Requests"
        }
    ]
}
